README.md
setup.cfg
setup.py
tmdr_distributions/Binomialdistribution.py
tmdr_distributions/Gaussiandistribution.py
tmdr_distributions/Generaldistribution.py
tmdr_distributions/__init__.py
tmdr_distributions.egg-info/PKG-INFO
tmdr_distributions.egg-info/SOURCES.txt
tmdr_distributions.egg-info/dependency_links.txt
tmdr_distributions.egg-info/not-zip-safe
tmdr_distributions.egg-info/top_level.txt